MANIFEST.in
README.rst
base.cfg
buildout.cfg
requirements.txt
setup.cfg
setup.py
versions.cfg
docs/HISTORY.txt
docs/INSTALL.txt
docs/LICENSE.GPL
docs/LICENSE.txt
rer/__init__.py
rer.subsites.egg-info/PKG-INFO
rer.subsites.egg-info/SOURCES.txt
rer.subsites.egg-info/dependency_links.txt
rer.subsites.egg-info/entry_points.txt
rer.subsites.egg-info/namespace_packages.txt
rer.subsites.egg-info/not-zip-safe
rer.subsites.egg-info/requires.txt
rer.subsites.egg-info/top_level.txt
rer/subsites/__init__.py
rer/subsites/configure.zcml
rer/subsites/i18n.sh
rer/subsites/testing.py
rer/subsites/browser/__init__.py
rer/subsites/browser/configure.zcml
rer/subsites/browser/layout.py
rer/subsites/browser/show_subsitescss.py
rer/subsites/browser/subsite.png
rer/subsites/browser/subsite_folder_utils.py
rer/subsites/browser/subsite_styles_form.py
rer/subsites/browser/viewlets.py
rer/subsites/browser/controlpanel/__init__.py
rer/subsites/browser/controlpanel/configure.zcml
rer/subsites/browser/controlpanel/controlpanel.py
rer/subsites/browser/viewlets/rer_subsite_title.pt
rer/subsites/interfaces/__init__.py
rer/subsites/interfaces/settings.py
rer/subsites/interfaces/subsite.py
rer/subsites/locales/rer.subsites.pot
rer/subsites/locales/it/LC_MESSAGES/rer.subsites.mo
rer/subsites/locales/it/LC_MESSAGES/rer.subsites.po
rer/subsites/profiles/default/actions.xml
rer/subsites/profiles/default/browserlayer.xml
rer/subsites/profiles/default/controlpanel.xml
rer/subsites/profiles/default/ersubsites-various.txt
rer/subsites/profiles/default/metadata.xml
rer/subsites/profiles/default/registry.xml
rer/subsites/profiles/default/rolemap.xml
rer/subsites/profiles/remove_colorpicker/registry.xml
rer/subsites/profiles/uninstall/browserlayer.xml
rer/subsites/profiles/uninstall/controlpanel.xml
rer/subsites/profiles/uninstall/registry.xml
rer/subsites/tests/__init__.py
rer/subsites/tests/test_enable_subsite.py
rer/subsites/tests/test_robot.py
rer/subsites/tests/test_setup.py
rer/subsites/tests/test_subsite_viewlet.py
rer/subsites/tests/robot/test_example.robot
rer/subsites/upgrades/__init__.py
rer/subsites/upgrades/configure.zcml
rer/subsites/upgrades/upgrades.py