Metadata-Version: 2.1
Name: rer.subsites
Version: 1.4.0
Summary: Subsites for ER portals
Home-page: https://rersvn.ente.regione.emr.it/svn/plone/prodotti/rer.subsites/
Author: RedTurtle Technology
Author-email: sviluppoplone@redturtle.it
License: GPL
Platform: UNKNOWN
Classifier: Framework :: Plone
Classifier: Framework :: Plone :: 5.0
Classifier: Framework :: Plone :: 5.1
Classifier: Intended Audience :: Developers
Classifier: License :: OSI Approved :: GNU General Public License (GPL)
Provides-Extra: test
